testing/mysql.py
testing_mysql-0.3.0.1.dist-info/METADATA
testing_mysql-0.3.0.1.dist-info/WHEEL
testing_mysql-0.3.0.1.dist-info/top_level.txt
testing_mysql-0.3.0.1.dist-info/RECORD
