Metadata-Version: 2.4
Name: testing.mysql
Version: 0.3.0.1
Summary: MySQL testing framework
Author-email: Joshua Haase <hahj87@gmail.com>
License-Expression: MIT
Requires-Python: >=3.6
Requires-Dist: docker
Provides-Extra: test
Requires-Dist: pytest; extra == "test"
